drb_impl_wXs/__init__.py
drb_impl_wXs/_version.py
drb_impl_wXs/exceptions.py
drb_impl_wXs/wXs_node.py
drb_impl_wXs-1.0.3.data/data/requirements.txt
drb_impl_wXs-1.0.3.dist-info/METADATA
drb_impl_wXs-1.0.3.dist-info/WHEEL
drb_impl_wXs-1.0.3.dist-info/top_level.txt
drb_impl_wXs-1.0.3.dist-info/RECORD
