Metadata-Version: 2.1
Name: drb-impl-wXs
Version: 1.0.3
Summary: DRB WXS OGC Service implementation
Home-page: https://gitlab.com/drb-python/impl/wXs
Author: GAEL Systems
Author-email: drb-python@gael.fr
License: UNKNOWN
Platform: UNKNOWN
Classifier: Programming Language :: Python :: 3.8
Classifier: License :: OSI Approved :: Apache Software License
Classifier: Operating System :: OS Independent
Requires-Python: >=3.8
Requires-Dist: requests (~=2.27.1)
Requires-Dist: drb (<1.1.0,>=1.0.4)
Requires-Dist: drb-impl-http (<1.1.0,>=1.0.4)
Requires-Dist: defusedxml (>=0.7.1)
Requires-Dist: drb-impl-json (<1.1.0,>=1.0.1)
Requires-Dist: drb-impl-xml (<1.1.0,>=1.0.0)
